hashball/__init__.py
hashball/chash.py
hashball/chash_exceptions.py
hashball/chash_visualize.py
hashball/hashball.py
hashball/testcases.py
hashball-0.0.5.dist-info/LICENSE
hashball-0.0.5.dist-info/METADATA
hashball-0.0.5.dist-info/WHEEL
hashball-0.0.5.dist-info/top_level.txt
hashball-0.0.5.dist-info/RECORD
